ecsm_tool/__init__.py
ecsm_tool/main.py
ecsm_tool/ecsm_cli/__init__.py
ecsm_tool/ecsm_cli/cli.py
ecsm_tool/ecsm_cli/cli_base.py
ecsm_tool/ecsm_cli/cli_images.py
ecsm_tool/ecsm_cli/cli_node.py
ecsm_tool/ecsm_cli/cli_tools.py
ecsm_tool/ecsm_core/__init__.py
ecsm_tool/ecsm_core/repo.py
tests/__init__.py
tests/test_cli.py
ecsm_tool-0.0.5.dist-info/LICENSE
ecsm_tool-0.0.5.dist-info/METADATA
ecsm_tool-0.0.5.dist-info/WHEEL
ecsm_tool-0.0.5.dist-info/entry_points.txt
ecsm_tool-0.0.5.dist-info/top_level.txt
ecsm_tool-0.0.5.dist-info/RECORD
