Metadata-Version: 2.1
Name: ecsm-tool
Version: 0.0.5
Summary: ECSM TOOLS
Author: liuyang.z
Author-email: chalks_arrival.0i@icloud.com
License: MIT
Keywords: ECSM,TOOLS,API
License-File: LICENSE
Requires-Dist: requests>=2.32.3
Requires-Dist: tqdm>=4.67.1
